logging_hj3415/__init__.py
logging_hj3415/_setup.py
logging_hj3415/pretty.py
logging_hj3415-1.0.2.dist-info/licenses/LICENSE
logging_hj3415-1.0.2.dist-info/WHEEL
logging_hj3415-1.0.2.dist-info/METADATA
logging_hj3415-1.0.2.dist-info/RECORD
