Metadata-Version: 2.4
Name: logging-hj3415
Version: 1.0.2
Summary: A logging library package built with Loguru
Keywords: example,demo
Author-email: Hyungjin Kim <hj3415@gmail.com>
Requires-Python: >=3.11
Classifier: Programming Language :: Python :: 3
Classifier: License :: OSI Approved :: MIT License
Classifier: Typing :: Typed
License-File: LICENSE
Requires-Dist: loguru>=0.7
